hashable_lru_cache/__init__.py
hashable_lru_cache/hashable_lru_cache.py
hashable_lru_cache/py.typed
hashable_lru_cache-0.1.4.dist-info/LICENSE
hashable_lru_cache-0.1.4.dist-info/WHEEL
hashable_lru_cache-0.1.4.dist-info/METADATA
hashable_lru_cache-0.1.4.dist-info/RECORD
